torchsr/__init__.py
torchsr/datasets/__init__.py
torchsr/datasets/benchmarks.py
torchsr/datasets/common.py
torchsr/datasets/div2k.py
torchsr/datasets/flickr2k.py
torchsr/datasets/realsr.py
torchsr/datasets/reds.py
torchsr/models/__init__.py
torchsr/models/carn.py
torchsr/models/direct.py
torchsr/models/edsr.py
torchsr/models/ninasr.py
torchsr/models/rcan.py
torchsr/models/rdn.py
torchsr/models/utils.py
torchsr/models/vdsr.py
torchsr/transforms/__init__.py
torchsr/transforms/transforms.py
aiarc-1.0.4.dist-info/LICENSE
aiarc-1.0.4.dist-info/METADATA
aiarc-1.0.4.dist-info/WHEEL
aiarc-1.0.4.dist-info/top_level.txt
aiarc-1.0.4.dist-info/RECORD
