Metadata-Version: 2.1
Name: aiarc
Version: 1.0.4
Summary: Super Resolution Networks for pytorch
Home-page: https://github.com/Coloquinte/torchSR
Author: Gabriel Gouvine
Author-email: gabriel.gouvine_GIT@m4x.org.com
License: MIT
Keywords: superresolution,pytorch,edsr,rcan,ninasr
Classifier: License :: OSI Approved :: MIT License
Classifier: Programming Language :: Python :: 3
Classifier: Intended Audience :: Science/Research
Classifier: Intended Audience :: Developers
License-File: LICENSE
Requires-Dist: torch (>=1.6)
Requires-Dist: torchvision (>=0.6)
